chatbot/__init__.py
chatbot/chatbot.py
chatbot_lite-0.1.2.dist-info/LICENSE
chatbot_lite-0.1.2.dist-info/METADATA
chatbot_lite-0.1.2.dist-info/WHEEL
chatbot_lite-0.1.2.dist-info/top_level.txt
chatbot_lite-0.1.2.dist-info/RECORD
