Metadata-Version: 2.1
Name: chatbot-lite
Version: 0.1.2
Summary: A simple chatbot
Home-page: https://github.com/Mahes2/chatbot-lite
Author: Mahes
Author-email: mahessawira@gmail.com
Classifier: Programming Language :: Python :: 3
Classifier: License :: OSI Approved :: MIT License
Classifier: Operating System :: OS Independent
Requires-Python: >=3.12
License-File: LICENSE
Requires-Dist: nltk >=3.9.1
Requires-Dist: certifi >=2024.8.30
